hiel/__init__.py
hiel/cli.py
hiel/services/__init__.py
hiel/services/bootstrap.py
hiel/services/github.py
hiel/utils/__init__.py
hiel/utils/constants.py
hiel/utils/enums.py
hiel-0.0.1.dist-info/entry_points.txt
hiel-0.0.1.dist-info/WHEEL
hiel-0.0.1.dist-info/METADATA
hiel-0.0.1.dist-info/RECORD
