Metadata-Version: 2.1
Name: hiel
Version: 0.0.1
Summary: a command line utility for bootstrapping projects with git
Home-page: https://github.com/BolajiOlajide/hiel
License: MIT
Author: Bolaji Olajide
Requires-Python: ==3.6.8
Classifier: License :: OSI Approved :: MIT License
Classifier: Programming Language :: Python :: 3
Classifier: Programming Language :: Python :: 3.6
Requires-Dist: requests (>=2.23.0,<3.0.0)
Requires-Dist: typer (>=0.1.1,<0.2.0)
Project-URL: Repository, https://github.com/BolajiOlajide/hiel
